{
  "ports": [
     {
         "id": 1,
         "port": "Padang",
         "country": "Indonesia"
      },
      {
         "id": 2,
         "port": "Pagny",
         "country": "France"
      },
      {
         "id": 3,
         "port": "Pago Pago",
         "country": "American Samoa"
      },
      {
         "id": 4,
         "port": "Paita",
         "country": "Peru"
      },
      {
         "id": 5,
         "port": "Palembang",
         "country": "Indonesia"
      },
      {
         "id": 6,
         "port": "Palermo",
         "country": "Italy"
      },
      {
         "id": 7,
         "port": "Palmerston North",
         "country": "New Zealand"
      },
      {
         "id": 8,
         "port": "Panama",
         "country": "Panama"
      },
      {
         "id": 9,
         "port": "Panjang",
         "country": "Indonesia"
      },
      {
         "id": 10,
         "port": "Panyu",
         "country": "China"
      },
      {
         "id": 11,
         "port": "Piraeus", 
         "country": "Greece"
      }
  ],
  "profile": {
    "name": "typicode"
  }
}
